[
    {
        "dia": "13-12-2022",
        "hora": "10:00",
        "motivo": "Envío de boletines de 2º de ciclos",
        "color": "red"
    },
    {
        "dia": "24-06-2023",
        "hora": "10:00",
        "motivo": "Envío de boletines extraordinaria de 2º de ciclos",
        "color": "orange"
    },
    {
        "dia": "19-12-2022",
        "hora": "10:00",
        "motivo": "Envío de boletines extraordinaria de 2º de ciclos. Alumnos con pendientes",
        "color": "yellow"
    },
    {
        "dia": "14-10-2022",
        "hora": "10:00",
        "motivo": "Comedor escolar: Plazo límite para firmar el anexo 8 (Firma del contrato)",
        "color": "green"
    },
    {
        "dia": "21-12-2022",
        "hora": "12:44",
        "motivo": "Clases particulares de diseño artístico con el nuevo profesor de artes plásticas",
        "color": "blue"
    },
    {
        "dia": "21-12-2022",
        "hora": "17:37",
        "motivo": "Reunión con los nuevos becarios de la empresa",
        "color": "orange"
    },
    {
        "dia": "21-05-2020",
        "hora": "10:44",
        "motivo": "Desayuno familiar",
        "color": "orange"
    },
    {
        "dia": "21-05-2020",
        "hora": "15:55",
        "motivo": "Entrevista con los miebros del nuevo plan de empresa",
        "color": "red"
    }
]
